ctkcomponents/__init__.py
ctkcomponents/ctk_components.py
ctkcomponents/src/icons/arrow.png
ctkcomponents/src/icons/close_black.png
ctkcomponents/src/icons/close_white.png
ctkcomponents/src/icons/error.png
ctkcomponents/src/icons/eye1_black.png
ctkcomponents/src/icons/eye1_white.png
ctkcomponents/src/icons/eye2_black.png
ctkcomponents/src/icons/eye2_white.png
ctkcomponents/src/icons/icon.png
ctkcomponents/src/icons/image.png
ctkcomponents/src/icons/image1.jpg
ctkcomponents/src/icons/image2.jpg
ctkcomponents/src/icons/image3.jpg
ctkcomponents/src/icons/info.png
ctkcomponents/src/icons/left.png
ctkcomponents/src/icons/loader.gif
ctkcomponents/src/icons/right.png
ctkcomponents/src/icons/warning.png
ctkcomponents/src/icons/warning2.png
ctkcomponents/src/util/CTkGif.py
ctkcomponents/src/util/window_position.py
ctkcomponents-0.4.dist-info/METADATA
ctkcomponents-0.4.dist-info/WHEEL
ctkcomponents-0.4.dist-info/entry_points.txt
ctkcomponents-0.4.dist-info/top_level.txt
ctkcomponents-0.4.dist-info/RECORD
