Metadata-Version: 2.1
Name: ctkcomponents
Version: 0.4
Requires-Dist: customtkinter ==5.2.2
Requires-Dist: pillow ==10.2.0
Requires-Dist: pywinstyles ==1.7
